cscwrapper/APIHandler.py
cscwrapper/CSC/templates/ApproveOrder.xml
cscwrapper/CSC/templates/AvailableSearches.xml
cscwrapper/CSC/templates/ContinueFiling.xml
cscwrapper/CSC/templates/CreateFiling.xml
cscwrapper/CSC/templates/GetAttachment.xml
cscwrapper/CSC/templates/GetChangedOrders.xml
cscwrapper/CSC/templates/GetDetailResults.xml
cscwrapper/CSC/templates/GetDocuments.xml
cscwrapper/CSC/templates/GetJurisdictions.xml
cscwrapper/CSC/templates/GetOrderInformation.xml
cscwrapper/CSC/templates/GetReport.xml
cscwrapper/CSC/templates/GetSummaryResults.xml
cscwrapper/CSC/templates/SetSelectedDetailResults.xml
cscwrapper/CSC/templates/SetSelectedSummaryResults.xml
cscwrapper/CSC/templates/SubmitOfflineSearch.xml
cscwrapper/CSC/templates/SubmitOnlineSearch.xml
cscwrapper/CSC/templates/TerminateFiling.xml
cscwrapper/CSC/templates/UpdateFiling.xml
cscwrapper/CSC/templates/UploadAttachment.xml
cscwrapper/CSC/templates/ValidateFiling.xml
cscwrapper/CSCWrapper.py
cscwrapper/__init__.py
cscwrapper/consts.py
cscwrapper-3.0.0.dist-info/LICENSE
cscwrapper-3.0.0.dist-info/METADATA
cscwrapper-3.0.0.dist-info/WHEEL
cscwrapper-3.0.0.dist-info/RECORD
